{
    "items": {
        "10654": [
            {
                "price": 10000,
                "world": "ESENKY"
            }
        ],
        "388": [
            {
                "price": 10000,
                "world": "ESENKY"
            }
        ],
        "390": [
            {
                "price": 10000,
                "world": "ESENKY"
            }
        ],
        "616": [
            {
                "price": 10000,
                "world": "ESENKY"
            }
        ],
        "9482": [
            {
                "price": 10000,
                "world": "ESENKY"
            }
        ]
    }
}