[{"accessible":false,"pos":[83,3],"price":5000,"time":"2026-04-17 02:32:01","timestamp":1776382321,"world":"JAJAN"},{"accessible":false,"pos":[27,42],"price":5000,"time":"2026-03-10 20:18:14","timestamp":1773163094,"world":"ZUG"},{"accessible":false,"pos":[16,39],"price":2999,"time":"2026-04-05 20:35:11","timestamp":1775410511,"world":"XBUYWING"},{"accessible":true,"pos":[70,47],"price":2500,"time":"2026-03-31 03:56:20","timestamp":1774918580,"world":"TOABI"},{"accessible":false,"pos":[19,7],"price":14000,"time":"2026-04-17 02:34:19","timestamp":1776382459,"world":"JAJAN"},{"accessible":true,"pos":[20,24],"price":5000,"time":"2026-04-16 01:03:12","timestamp":1776290592,"world":"WJAW"},{"accessible":true,"pos":[93,2],"price":8000,"time":"2026-04-22 16:50:43","timestamp":1776865843,"world":"L0S"},{"accessible":true,"pos":[23,24],"price":20000,"time":"2026-04-22 16:50:56","timestamp":1776865856,"world":"WJAW"},{"accessible":true,"pos":[49,35],"price":9999,"time":"2026-04-26 19:58:39","timestamp":1777222719,"world":"BUYSUNBLADEPERM"}]