[{"accessible":true,"pos":[46,22],"price":15000,"time":"2026-03-15 23:40:06","timestamp":1773607206,"world":"JAJAN"},{"accessible":true,"pos":[69,36],"price":8500,"time":"2026-03-27 01:37:55","timestamp":1774564675,"world":"BBAKMB"},{"accessible":false,"pos":[18,41],"price":10599,"time":"2026-03-25 14:22:20","timestamp":1774437740,"world":"GROCERY"},{"accessible":false,"pos":[37,36],"price":7999,"time":"2026-03-20 01:05:41","timestamp":1773957941,"world":"XBUYWING"},{"accessible":true,"pos":[29,41],"price":11500,"time":"2026-03-21 20:33:36","timestamp":1774114416,"world":"TEYK"},{"accessible":false,"pos":[52,31],"price":10000,"time":"2026-03-25 02:28:57","timestamp":1774394937,"world":"CLOTHES"},{"accessible":true,"pos":[51,37],"price":8000,"time":"2026-03-30 19:59:40","timestamp":1774889980,"world":"CHC"}]