[{"accessible":true,"pos":[29,22],"price":-1,"time":"2026-04-27 03:34:36","timestamp":1777250076,"world":"SUR"},{"accessible":false,"pos":[60,39],"price":-2,"time":"2026-04-10 22:19:58","timestamp":1775848798,"world":"CURE2WL"},{"accessible":true,"pos":[18,16],"price":-1,"time":"2026-03-14 03:30:49","timestamp":1773448249,"world":"GGH"},{"accessible":true,"pos":[72,22],"price":-5,"time":"2026-03-14 04:01:40","timestamp":1773450100,"world":"QU4C"},{"accessible":false,"pos":[92,22],"price":2,"time":"2026-03-27 17:57:53","timestamp":1774623473,"world":"MEDICINE"},{"accessible":true,"pos":[17,21],"price":-1,"time":"2026-03-16 00:05:04","timestamp":1773608704,"world":"JUMBI"},{"accessible":true,"pos":[32,27],"price":-10,"time":"2026-04-01 12:10:51","timestamp":1775034651,"world":"TIGUL"},{"accessible":false,"pos":[45,35],"price":1,"time":"2026-03-15 03:43:43","timestamp":1773535423,"world":"VACCINATION"},{"accessible":true,"pos":[30,44],"price":-4,"time":"2026-03-30 19:35:32","timestamp":1774888532,"world":"C3RT"},{"accessible":true,"pos":[88,18],"price":-1,"time":"2026-03-17 21:29:43","timestamp":1773772183,"world":"PETM"},{"accessible":true,"pos":[42,18],"price":100,"time":"2026-03-20 16:39:57","timestamp":1774013997,"world":"DUSTAW"},{"accessible":false,"pos":[27,24],"price":1,"time":"2026-03-23 14:54:29","timestamp":1774266869,"world":"APOTEKER"},{"accessible":true,"pos":[28,22],"price":-15,"time":"2026-03-23 21:43:41","timestamp":1774291421,"world":"JALANKA"},{"accessible":true,"pos":[14,46],"price":-1,"time":"2026-03-25 02:07:25","timestamp":1774393645,"world":"FOLE"},{"accessible":false,"pos":[18,48],"price":1,"time":"2026-03-25 02:08:50","timestamp":1774393730,"world":"UCCI"},{"accessible":false,"pos":[29,38],"price":-2,"time":"2026-03-26 06:53:23","timestamp":1774497203,"world":"CUREC"},{"accessible":false,"pos":[7,48],"price":-1,"time":"2026-03-25 23:40:39","timestamp":1774471239,"world":"SHOPTOPIA"},{"accessible":false,"pos":[94,39],"price":-1,"time":"2026-03-31 00:51:03","timestamp":1774907463,"world":"REVIVE"},{"accessible":true,"pos":[76,41],"price":-5,"time":"2026-03-27 10:13:29","timestamp":1774595609,"world":"PEMEG"},{"accessible":true,"pos":[36,42],"price":-4,"time":"2026-03-27 22:00:55","timestamp":1774638055,"world":"SANKOLA"},{"accessible":true,"pos":[59,46],"price":3,"time":"2026-03-28 20:21:00","timestamp":1774718460,"world":"PULA6"},{"accessible":true,"pos":[70,19],"price":-1,"time":"2026-04-11 03:12:48","timestamp":1775866368,"world":"DAJAAL"},{"accessible":true,"pos":[57,43],"price":-30,"time":"2026-03-29 20:40:12","timestamp":1774806012,"world":"PBEDX"},{"accessible":true,"pos":[45,22],"price":-20,"time":"2026-03-30 03:21:28","timestamp":1774830088,"world":"RAIKOXZ"},{"accessible":true,"pos":[16,27],"price":-1,"time":"2026-03-31 05:19:09","timestamp":1774923549,"world":"DTOTO"},{"accessible":true,"pos":[31,30],"price":-1,"time":"2026-04-17 22:38:00","timestamp":1776454680,"world":"MKMEM"},{"accessible":false,"pos":[94,36],"price":-1,"time":"2026-04-29 20:42:09","timestamp":1777484529,"world":"REVIVE"},{"accessible":false,"pos":[33,49],"price":-5,"time":"2026-04-22 19:58:57","timestamp":1776877137,"world":"SURG2WL"},{"accessible":true,"pos":[30,51],"price":-5,"time":"2026-04-02 21:37:40","timestamp":1775155060,"world":"R3G9"},{"accessible":true,"pos":[58,21],"price":-6,"time":"2026-04-03 10:56:05","timestamp":1775202965,"world":"MARTJC"},{"accessible":true,"pos":[27,46],"price":-3,"time":"2026-04-03 14:21:31","timestamp":1775215291,"world":"WIFKY"},{"accessible":true,"pos":[21,9],"price":-1,"time":"2026-04-03 14:47:31","timestamp":1775216851,"world":"JUYTINH"},{"accessible":true,"pos":[81,16],"price":-5,"time":"2026-04-03 14:53:48","timestamp":1775217228,"world":"0X3"},{"accessible":true,"pos":[18,48],"price":-1,"time":"2026-04-04 02:57:17","timestamp":1775260637,"world":"GLOIR"},{"accessible":false,"pos":[73,48],"price":2,"time":"2026-04-04 17:30:56","timestamp":1775313056,"world":"RAMEAN"},{"accessible":true,"pos":[53,49],"price":-1,"time":"2026-04-05 23:16:45","timestamp":1775420205,"world":"SUNIBA"},{"accessible":true,"pos":[55,33],"price":-2,"time":"2026-04-08 11:51:39","timestamp":1775638299,"world":"7DR3"},{"accessible":true,"pos":[31,40],"price":-10,"time":"2026-04-08 21:55:17","timestamp":1775674517,"world":"CUREBOI"},{"accessible":false,"pos":[43,18],"price":-2,"time":"2026-04-09 18:23:43","timestamp":1775748223,"world":"N7"},{"accessible":true,"pos":[77,42],"price":-1,"time":"2026-04-10 01:35:57","timestamp":1775774157,"world":"AGST"},{"accessible":true,"pos":[38,48],"price":-1,"time":"2026-04-11 00:42:21","timestamp":1775857341,"world":"VJVG"},{"accessible":true,"pos":[31,53],"price":-10,"time":"2026-04-11 15:41:45","timestamp":1775911305,"world":"HEDCRIME1"},{"accessible":true,"pos":[87,49],"price":-10,"time":"2026-04-14 21:18:41","timestamp":1776190721,"world":"WESTELLE"},{"accessible":true,"pos":[14,40],"price":6,"time":"2026-04-15 12:44:40","timestamp":1776246280,"world":"SULL"},{"accessible":true,"pos":[10,14],"price":-1,"time":"2026-04-27 02:07:08","timestamp":1777244828,"world":"PETM"},{"accessible":false,"pos":[45,10],"price":-4,"time":"2026-04-19 19:01:55","timestamp":1776614515,"world":"CICP"},{"accessible":true,"pos":[29,39],"price":-1,"time":"2026-04-20 00:04:22","timestamp":1776632662,"world":"RACENW"},{"accessible":true,"pos":[81,13],"price":-1,"time":"2026-04-21 23:35:19","timestamp":1776803719,"world":"HOSPITAL50"},{"accessible":true,"pos":[20,18],"price":200,"time":"2026-04-22 16:55:01","timestamp":1776866101,"world":"WJAW"},{"accessible":true,"pos":[28,22],"price":-15,"time":"2026-04-25 23:18:29","timestamp":1777148309,"world":"BFWV"},{"accessible":true,"pos":[23,31],"price":-1,"time":"2026-04-26 19:59:03","timestamp":1777222743,"world":"OOFMARKET"},{"accessible":true,"pos":[75,43],"price":-1,"time":"2026-04-29 00:42:31","timestamp":1777412551,"world":"JOHAV"},{"accessible":true,"pos":[60,33],"price":-1,"time":"2026-04-29 20:54:17","timestamp":1777485257,"world":"OBATK"}]