[{"accessible":false,"pos":[54,40],"price":45,"time":"2026-03-20 23:23:41","timestamp":1774038221,"world":"GEP214"},{"accessible":true,"pos":[85,41],"price":55,"time":"2026-03-20 15:29:28","timestamp":1774009768,"world":"ZUAZ"},{"accessible":true,"pos":[46,16],"price":80,"time":"2026-03-15 23:37:04","timestamp":1773607024,"world":"JAJAN"},{"accessible":true,"pos":[36,40],"price":70,"time":"2026-03-17 21:22:38","timestamp":1773771758,"world":"C3RT"},{"accessible":false,"pos":[62,21],"price":105,"time":"2026-03-19 15:08:45","timestamp":1773922125,"world":"WTU"},{"accessible":false,"pos":[7,9],"price":75,"time":"2026-03-26 23:28:16","timestamp":1774556896,"world":"BUYWING"},{"accessible":false,"pos":[62,38],"price":20000,"time":"2026-03-20 02:11:21","timestamp":1773961881,"world":"LIWSA"},{"accessible":true,"pos":[71,24],"price":500,"time":"2026-03-20 16:43:33","timestamp":1774014213,"world":"DUSTAW"},{"accessible":true,"pos":[38,35],"price":65,"time":"2026-03-21 20:31:17","timestamp":1774114277,"world":"TEYK"},{"accessible":false,"pos":[15,48],"price":40,"time":"2026-03-23 16:45:48","timestamp":1774273548,"world":"YO"},{"accessible":false,"pos":[43,31],"price":150,"time":"2026-03-25 02:28:47","timestamp":1774394927,"world":"CLOTHES"},{"accessible":true,"pos":[55,36],"price":55,"time":"2026-03-27 01:37:38","timestamp":1774564658,"world":"BBAKMB"},{"accessible":true,"pos":[42,33],"price":42,"time":"2026-03-29 02:44:10","timestamp":1774741450,"world":"KHMERSHOP"},{"accessible":true,"pos":[47,43],"price":50,"time":"2026-03-29 16:30:11","timestamp":1774791011,"world":"LIHEM"},{"accessible":true,"pos":[79,37],"price":45,"time":"2026-03-29 21:15:44","timestamp":1774808144,"world":"CIDD"}]