[{"accessible":true,"pos":[89,46],"price":-10,"time":"2026-03-13 22:38:46","timestamp":1773430726,"world":"H2QX"},{"accessible":true,"pos":[60,52],"price":-50,"time":"2026-03-19 17:27:42","timestamp":1773930462,"world":"MINES"},{"accessible":false,"pos":[82,45],"price":-100,"time":"2026-04-02 18:51:05","timestamp":1775145065,"world":"BLOCKWOW"},{"accessible":true,"pos":[63,47],"price":-1,"time":"2026-04-05 08:49:26","timestamp":1775368166,"world":"SHOPCHASER"},{"accessible":true,"pos":[16,45],"price":-10,"time":"2026-04-24 23:40:42","timestamp":1777063242,"world":"TROPIQ"},{"accessible":true,"pos":[16,45],"price":-10,"time":"2026-04-25 00:05:14","timestamp":1777064714,"world":"BUYPEPPERV2"},{"accessible":true,"pos":[7,43],"price":-15,"time":"2026-04-27 03:31:09","timestamp":1777249869,"world":"SWEDISHSTORE"},{"accessible":true,"pos":[84,37],"price":-20,"time":"2026-04-29 21:18:44","timestamp":1777486724,"world":"JOHAV"}]