[{"accessible":true,"pos":[72,48],"price":15,"time":"2026-03-15 23:55:42","timestamp":1773608142,"world":"JAJAN"},{"accessible":false,"pos":[75,28],"price":4,"time":"2026-03-25 02:28:25","timestamp":1774394905,"world":"CLOTHES"},{"accessible":true,"pos":[79,22],"price":-1,"time":"2026-04-06 02:09:50","timestamp":1775430590,"world":"IYB"},{"accessible":true,"pos":[67,43],"price":-1,"time":"2026-04-08 01:40:33","timestamp":1775601633,"world":"SELLCHECKP"},{"accessible":true,"pos":[16,33],"price":-5,"time":"2026-04-25 20:50:32","timestamp":1777139432,"world":"VENDALL"},{"accessible":false,"pos":[28,20],"price":-1,"time":"2026-04-19 19:02:02","timestamp":1776614522,"world":"CICP"}]