[{"accessible":true,"pos":[80,13],"price":-4,"time":"2026-03-27 10:10:13","timestamp":1774595413,"world":"MARTN"},{"accessible":false,"pos":[52,42],"price":-1,"time":"2026-03-30 00:09:37","timestamp":1774818577,"world":"1GO"},{"accessible":true,"pos":[30,36],"price":-1,"time":"2026-04-01 22:57:19","timestamp":1775073439,"world":"DRLACHIMOLALA"},{"accessible":true,"pos":[22,19],"price":-1,"time":"2026-04-02 15:36:11","timestamp":1775133371,"world":"24SF"},{"accessible":false,"pos":[66,45],"price":-5,"time":"2026-04-05 20:12:00","timestamp":1775409120,"world":"JMRWR"}]