[{"accessible":true,"pos":[35,27],"price":-10,"time":"2026-03-18 22:36:34","timestamp":1773862594,"world":"ALTISHOP"},{"accessible":false,"pos":[80,44],"price":-1,"time":"2026-03-29 21:16:36","timestamp":1774808196,"world":"SAMAA"},{"accessible":true,"pos":[19,4],"price":-5,"time":"2026-04-05 19:57:50","timestamp":1775408270,"world":"LIKEMATH"},{"accessible":true,"pos":[83,6],"price":-10,"time":"2026-04-09 01:02:55","timestamp":1775685775,"world":"FORSALE"},{"accessible":false,"pos":[45,8],"price":-7,"time":"2026-04-15 20:23:42","timestamp":1776273822,"world":"PUBBI"},{"accessible":true,"pos":[38,43],"price":1,"time":"2026-04-16 01:02:08","timestamp":1776290528,"world":"DOVM1"},{"accessible":true,"pos":[54,11],"price":-10,"time":"2026-04-20 21:41:20","timestamp":1776710480,"world":"BUYSHOP"},{"accessible":true,"pos":[63,43],"price":-5,"time":"2026-04-22 22:03:16","timestamp":1776884596,"world":"VOYBO"},{"accessible":true,"pos":[33,47],"price":-4,"time":"2026-04-23 01:44:40","timestamp":1776897880,"world":"CORDON"},{"accessible":false,"pos":[12,39],"price":-10,"time":"2026-04-25 19:45:48","timestamp":1777135548,"world":"BUYQ"},{"accessible":true,"pos":[48,49],"price":-5,"time":"2026-04-26 01:39:02","timestamp":1777156742,"world":"PADIA"}]