[{"accessible":false,"pos":[59,45],"price":3,"time":"2026-03-13 02:47:10","timestamp":1773359230,"world":"CURE2WL"},{"accessible":false,"pos":[24,24],"price":8,"time":"2026-03-14 15:36:00","timestamp":1773491760,"world":"MEDICINE"},{"accessible":false,"pos":[25,39],"price":4,"time":"2026-03-13 02:50:06","timestamp":1773359406,"world":"BUYSURGEONS"},{"accessible":true,"pos":[17,18],"price":15,"time":"2026-03-14 03:30:57","timestamp":1773448257,"world":"GGH"},{"accessible":true,"pos":[75,18],"price":2,"time":"2026-03-14 04:01:22","timestamp":1773450082,"world":"QU4C"}]