[{"accessible":true,"pos":[88,1],"price":80,"time":"2026-03-09 19:07:04","timestamp":1773072424,"world":"JAJAN"},{"accessible":false,"pos":[34,18],"price":185,"time":"2026-03-19 15:06:45","timestamp":1773922005,"world":"WTU"},{"accessible":true,"pos":[87,36],"price":250,"time":"2026-03-19 15:06:47","timestamp":1773922007,"world":"JOYN"},{"accessible":false,"pos":[84,48],"price":185,"time":"2026-03-19 15:24:11","timestamp":1773923051,"world":"WTU"},{"accessible":false,"pos":[25,42],"price":50,"time":"2026-04-05 20:36:33","timestamp":1775410593,"world":"XBUYWING"},{"accessible":true,"pos":[64,30],"price":180,"time":"2026-03-21 04:10:07","timestamp":1774055407,"world":"SPIKED"},{"accessible":true,"pos":[39,24],"price":20,"time":"2026-03-29 18:13:09","timestamp":1774797189,"world":"DAJAAL"},{"accessible":false,"pos":[68,52],"price":70,"time":"2026-04-05 17:55:19","timestamp":1775400919,"world":"STOREE"}]