[{"accessible":false,"pos":[75,48],"price":180,"time":"2026-03-11 20:38:04","timestamp":1773250684,"world":"YYKUN"},{"accessible":false,"pos":[30,46],"price":190,"time":"2026-03-20 23:24:56","timestamp":1774038296,"world":"GEP214"},{"accessible":false,"pos":[31,46],"price":190,"time":"2026-03-20 23:24:57","timestamp":1774038297,"world":"GEP214"},{"accessible":true,"pos":[81,23],"price":225,"time":"2026-03-30 09:54:41","timestamp":1774853681,"world":"YPR"},{"accessible":true,"pos":[26,42],"price":180,"time":"2026-03-18 01:21:45","timestamp":1773786105,"world":"MANAV"}]