[{"accessible":true,"pos":[48,16],"price":3500,"time":"2026-03-30 19:51:26","timestamp":1774889486,"world":"CHC"},{"accessible":true,"pos":[60,31],"price":3000,"time":"2026-03-10 20:15:32","timestamp":1773162932,"world":"ZUG"},{"accessible":true,"pos":[58,34],"price":12000,"time":"2026-03-15 23:47:10","timestamp":1773607630,"world":"JAJAN"},{"accessible":false,"pos":[16,21],"price":2999,"time":"2026-04-05 20:29:50","timestamp":1775410190,"world":"XBUYWING"},{"accessible":true,"pos":[39,35],"price":2099,"time":"2026-03-29 02:45:15","timestamp":1774741515,"world":"KHMERSHOP"}]