[{"accessible":true,"pos":[78,39],"price":20,"time":"2026-03-24 17:15:42","timestamp":1774361742,"world":"88BB"},{"accessible":true,"pos":[28,51],"price":35,"time":"2026-03-24 19:18:17","timestamp":1774369097,"world":"AWBLE"},{"accessible":true,"pos":[51,43],"price":100,"time":"2026-03-28 21:15:12","timestamp":1774721712,"world":"EMTBF"},{"accessible":false,"pos":[32,48],"price":10,"time":"2026-04-02 18:51:48","timestamp":1775145108,"world":"BLOCKWOW"},{"accessible":false,"pos":[66,20],"price":20,"time":"2026-04-03 01:46:14","timestamp":1775169974,"world":"BUYEYES5"},{"accessible":false,"pos":[1,10],"price":8,"time":"2026-04-08 11:38:00","timestamp":1775637480,"world":"7DR3"},{"accessible":true,"pos":[26,49],"price":-20,"time":"2026-04-08 14:06:31","timestamp":1775646391,"world":"WBOLO"},{"accessible":true,"pos":[80,48],"price":100,"time":"2026-04-09 01:09:10","timestamp":1775686150,"world":"FORSALE"},{"accessible":true,"pos":[78,39],"price":15,"time":"2026-04-24 23:38:31","timestamp":1777063111,"world":"TROPIQ"}]