[{"accessible":true,"pos":[27,25],"price":11000,"time":"2026-03-30 19:55:00","timestamp":1774889700,"world":"CHC"},{"accessible":false,"pos":[40,25],"price":15000,"time":"2026-03-31 03:59:32","timestamp":1774918772,"world":"NNUT"},{"accessible":true,"pos":[38,31],"price":19999,"time":"2026-03-15 23:44:42","timestamp":1773607482,"world":"JAJAN"},{"accessible":false,"pos":[76,18],"price":19999,"time":"2026-04-05 20:29:20","timestamp":1775410160,"world":"XBUYWING"},{"accessible":true,"pos":[53,47],"price":20000,"time":"2026-03-21 20:36:47","timestamp":1774114607,"world":"TEYK"},{"accessible":false,"pos":[59,42],"price":19900,"time":"2026-03-25 03:38:21","timestamp":1774399101,"world":"EGO"},{"accessible":false,"pos":[25,6],"price":19999,"time":"2026-04-05 20:26:03","timestamp":1775409963,"world":"XBUYWING"},{"accessible":true,"pos":[75,46],"price":16000,"time":"2026-04-05 21:41:30","timestamp":1775414490,"world":"VCNA11"}]