[{"accessible":true,"pos":[26,7],"price":10,"time":"2026-03-15 23:32:04","timestamp":1773606724,"world":"JAJAN"},{"accessible":false,"pos":[20,36],"price":-2,"time":"2026-03-08 22:44:42","timestamp":1772999082,"world":"XX3"},{"accessible":true,"pos":[70,18],"price":-1,"time":"2026-03-17 21:29:24","timestamp":1773772164,"world":"PETM"},{"accessible":true,"pos":[37,31],"price":-2,"time":"2026-03-17 21:31:06","timestamp":1773772266,"world":"ECDY1"},{"accessible":false,"pos":[63,28],"price":-1,"time":"2026-03-19 14:59:25","timestamp":1773921565,"world":"BUYHAT"}]