[{"accessible":true,"pos":[32,15],"price":2,"time":"2026-03-24 16:58:14","timestamp":1774360694,"world":"88BB"},{"accessible":true,"pos":[16,28],"price":-1,"time":"2026-03-30 00:32:15","timestamp":1774819935,"world":"56X"},{"accessible":true,"pos":[10,10],"price":2,"time":"2026-03-31 01:21:24","timestamp":1774909284,"world":"BLOCKQO"},{"accessible":true,"pos":[8,12],"price":1,"time":"2026-04-05 19:57:56","timestamp":1775408276,"world":"EYEM"},{"accessible":true,"pos":[32,42],"price":5,"time":"2026-04-07 22:16:21","timestamp":1775589381,"world":"REACT"},{"accessible":true,"pos":[32,15],"price":1,"time":"2026-04-09 15:34:24","timestamp":1775738064,"world":"TROPIQ"}]