[{"accessible":true,"pos":[77,46],"price":25,"time":"2026-03-08 13:19:18","timestamp":1772965158,"world":"H2QX"},{"accessible":false,"pos":[12,1],"price":-1,"time":"2026-03-30 19:48:26","timestamp":1774889306,"world":"CHC"},{"accessible":true,"pos":[29,41],"price":30,"time":"2026-03-24 17:16:23","timestamp":1774361783,"world":"88BB"},{"accessible":false,"pos":[30,39],"price":100,"time":"2026-03-30 00:08:40","timestamp":1774818520,"world":"1GO"},{"accessible":true,"pos":[29,44],"price":15,"time":"2026-04-01 22:58:13","timestamp":1775073493,"world":"DRLACHIMOLALA"},{"accessible":true,"pos":[36,9],"price":30,"time":"2026-04-02 23:50:18","timestamp":1775163018,"world":"SIGMA"},{"accessible":true,"pos":[71,46],"price":39,"time":"2026-04-03 22:04:53","timestamp":1775243093,"world":"BLOCKOK3"},{"accessible":true,"pos":[35,40],"price":8,"time":"2026-04-04 02:57:46","timestamp":1775260666,"world":"ARAR"},{"accessible":true,"pos":[73,16],"price":20,"time":"2026-04-05 19:58:46","timestamp":1775408326,"world":"PAEKO"}]