[{"accessible":true,"pos":[28,48],"price":30,"time":"2026-03-15 23:55:03","timestamp":1773608103,"world":"JAJAN"},{"accessible":true,"pos":[13,22],"price":-3,"time":"2026-03-17 21:26:19","timestamp":1773771979,"world":"ECDY1"},{"accessible":true,"pos":[85,34],"price":-3,"time":"2026-03-17 21:33:09","timestamp":1773772389,"world":"ECDY1"},{"accessible":false,"pos":[38,25],"price":-1,"time":"2026-03-19 14:58:25","timestamp":1773921505,"world":"BUYHAT"},{"accessible":false,"pos":[1,9],"price":25,"time":"2026-03-19 15:01:09","timestamp":1773921669,"world":"WTU"},{"accessible":true,"pos":[18,40],"price":-6,"time":"2026-03-25 21:06:50","timestamp":1774462010,"world":"D0CII"},{"accessible":true,"pos":[72,11],"price":-1,"time":"2026-04-02 15:38:41","timestamp":1775133521,"world":"VENDML"},{"accessible":true,"pos":[2,38],"price":-1,"time":"2026-04-04 03:07:17","timestamp":1775261237,"world":"NOOBV"}]