[{"accessible":true,"pos":[34,50],"price":80,"time":"2026-03-15 23:56:32","timestamp":1773608192,"world":"JAJAN"},{"accessible":false,"pos":[79,51],"price":25,"time":"2026-03-16 13:56:07","timestamp":1773658567,"world":"PHIRS"},{"accessible":false,"pos":[60,48],"price":235,"time":"2026-03-19 15:23:44","timestamp":1773923024,"world":"WTU"},{"accessible":true,"pos":[60,52],"price":20,"time":"2026-03-20 00:53:54","timestamp":1773957234,"world":"SINIVU"},{"accessible":true,"pos":[11,41],"price":50,"time":"2026-04-10 02:22:28","timestamp":1775776948,"world":"GYYS"},{"accessible":true,"pos":[74,45],"price":50,"time":"2026-04-28 01:35:24","timestamp":1777329324,"world":"TWR"}]