[{"accessible":false,"pos":[65,22],"price":210,"time":"2026-03-31 03:59:20","timestamp":1774918760,"world":"NNUT"},{"accessible":false,"pos":[15,39],"price":145,"time":"2026-04-05 21:38:27","timestamp":1775414307,"world":"EGO"},{"accessible":true,"pos":[61,31],"price":55,"time":"2026-03-29 02:43:43","timestamp":1774741423,"world":"KHMERSHOP"},{"accessible":true,"pos":[81,43],"price":850,"time":"2026-04-05 21:40:36","timestamp":1775414436,"world":"VCNA11"},{"accessible":true,"pos":[18,39],"price":50,"time":"2026-04-09 15:55:20","timestamp":1775739320,"world":"AVARO"}]