[{"accessible":true,"pos":[39,7],"price":6599,"time":"2026-04-09 15:54:49","timestamp":1775739289,"world":"JAJAN"},{"accessible":true,"pos":[41,31],"price":4000,"time":"2026-04-04 03:04:03","timestamp":1775261043,"world":"CHC"},{"accessible":true,"pos":[51,32],"price":3650,"time":"2026-04-11 00:42:52","timestamp":1775857372,"world":"YPR"},{"accessible":true,"pos":[86,31],"price":4000,"time":"2026-03-16 14:02:48","timestamp":1773658968,"world":"YUKJ"},{"accessible":false,"pos":[45,41],"price":6299,"time":"2026-03-18 21:05:06","timestamp":1773857106,"world":"GROCERY"},{"accessible":true,"pos":[32,44],"price":7000,"time":"2026-03-21 20:35:05","timestamp":1774114505,"world":"TEYK"},{"accessible":false,"pos":[27,47],"price":1750,"time":"2026-04-01 05:25:13","timestamp":1775010313,"world":"YO"},{"accessible":true,"pos":[77,32],"price":6000,"time":"2026-04-07 21:20:03","timestamp":1775586003,"world":"GBCS"},{"accessible":false,"pos":[43,48],"price":3999,"time":"2026-04-05 20:39:17","timestamp":1775410757,"world":"XBUYWING"},{"accessible":true,"pos":[74,23],"price":3500,"time":"2026-04-06 00:40:06","timestamp":1775425206,"world":"BWOISS"},{"accessible":false,"pos":[34,39],"price":3000,"time":"2026-04-06 19:50:40","timestamp":1775494240,"world":"KSACHEAP"},{"accessible":false,"pos":[37,48],"price":6000,"time":"2026-04-08 14:15:38","timestamp":1775646938,"world":"BUYWINGS"}]