[{"accessible":true,"pos":[54,40],"price":-1,"time":"2026-03-13 22:37:06","timestamp":1773430626,"world":"H2QX"},{"accessible":false,"pos":[97,21],"price":1500,"time":"2026-03-08 21:20:36","timestamp":1772994036,"world":"BUYIOTM"},{"accessible":true,"pos":[73,26],"price":-2,"time":"2026-03-18 01:23:25","timestamp":1773786205,"world":"SLOU"},{"accessible":true,"pos":[84,33],"price":-1,"time":"2026-03-24 17:11:02","timestamp":1774361462,"world":"88BB"},{"accessible":true,"pos":[53,28],"price":-1,"time":"2026-03-31 01:25:30","timestamp":1774909530,"world":"BLOCKQO"}]