[{"accessible":true,"pos":[35,28],"price":11,"time":"2026-03-16 00:15:18","timestamp":1773609318,"world":"SUR"},{"accessible":false,"pos":[48,45],"price":15,"time":"2026-04-10 22:23:21","timestamp":1775849001,"world":"CURE2WL"},{"accessible":false,"pos":[27,37],"price":15,"time":"2026-03-13 02:49:51","timestamp":1773359391,"world":"BUYSURGEONS"},{"accessible":true,"pos":[41,44],"price":9,"time":"2026-03-13 02:50:10","timestamp":1773359410,"world":"TALLE"},{"accessible":true,"pos":[14,24],"price":20,"time":"2026-03-14 03:31:20","timestamp":1773448280,"world":"GGH"},{"accessible":true,"pos":[33,48],"price":9,"time":"2026-03-13 16:43:11","timestamp":1773409391,"world":"SUHARU"},{"accessible":true,"pos":[52,15],"price":10,"time":"2026-03-14 04:00:58","timestamp":1773450058,"world":"QU4C"},{"accessible":true,"pos":[45,37],"price":10,"time":"2026-03-14 03:03:21","timestamp":1773446601,"world":"URFAV"},{"accessible":false,"pos":[55,22],"price":9,"time":"2026-03-14 03:26:02","timestamp":1773447962,"world":"SURGDEZZ"},{"accessible":false,"pos":[20,18],"price":20,"time":"2026-03-27 17:57:11","timestamp":1774623431,"world":"MEDICINE"},{"accessible":true,"pos":[42,48],"price":25,"time":"2026-03-14 17:31:42","timestamp":1773498702,"world":"WABAH"},{"accessible":true,"pos":[43,46],"price":9,"time":"2026-03-15 03:45:39","timestamp":1773535539,"world":"WEJE"},{"accessible":true,"pos":[63,46],"price":11,"time":"2026-03-15 03:45:45","timestamp":1773535545,"world":"WEJE"},{"accessible":true,"pos":[48,31],"price":10,"time":"2026-03-15 23:29:04","timestamp":1773606544,"world":"ACURE"},{"accessible":true,"pos":[39,28],"price":10,"time":"2026-03-23 21:44:54","timestamp":1774291494,"world":"JALANKA"},{"accessible":true,"pos":[40,23],"price":10,"time":"2026-03-24 17:04:29","timestamp":1774361069,"world":"88BB"},{"accessible":false,"pos":[23,27],"price":15,"time":"2026-03-23 14:54:35","timestamp":1774266875,"world":"APOTEKER"},{"accessible":false,"pos":[47,45],"price":11,"time":"2026-04-01 01:02:00","timestamp":1774994520,"world":"2WLCURES"},{"accessible":false,"pos":[20,42],"price":15,"time":"2026-03-26 06:54:02","timestamp":1774497242,"world":"CUREC"},{"accessible":false,"pos":[79,32],"price":15,"time":"2026-03-31 00:49:52","timestamp":1774907392,"world":"REVIVE"},{"accessible":true,"pos":[82,25],"price":20,"time":"2026-03-29 21:51:03","timestamp":1774810263,"world":"VNDXIEE"},{"accessible":true,"pos":[10,37],"price":10,"time":"2026-03-31 01:27:00","timestamp":1774909620,"world":"BLOCKQO"},{"accessible":false,"pos":[81,30],"price":15,"time":"2026-04-11 16:42:39","timestamp":1775914959,"world":"REVIVE"},{"accessible":false,"pos":[33,46],"price":10,"time":"2026-04-02 09:52:14","timestamp":1775112734,"world":"SURG2WL"},{"accessible":true,"pos":[40,23],"price":15,"time":"2026-04-02 12:39:29","timestamp":1775122769,"world":"VENDQE"},{"accessible":false,"pos":[10,30],"price":2,"time":"2026-04-02 18:45:56","timestamp":1775144756,"world":"BLOCKWOW"},{"accessible":true,"pos":[21,30],"price":20,"time":"2026-04-02 23:57:01","timestamp":1775163421,"world":"SIGMA"},{"accessible":true,"pos":[71,21],"price":11,"time":"2026-04-04 00:02:25","timestamp":1775250145,"world":"METABGL"},{"accessible":true,"pos":[58,28],"price":9,"time":"2026-04-04 00:03:42","timestamp":1775250222,"world":"PNHW"},{"accessible":true,"pos":[62,28],"price":9,"time":"2026-04-04 00:07:50","timestamp":1775250470,"world":"PNHW"},{"accessible":true,"pos":[62,11],"price":1000,"time":"2026-04-05 08:37:35","timestamp":1775367455,"world":"SHOPCHASER"},{"accessible":true,"pos":[6,20],"price":15,"time":"2026-04-05 19:59:53","timestamp":1775408393,"world":"PAEKO"},{"accessible":true,"pos":[37,50],"price":12,"time":"2026-04-05 21:27:06","timestamp":1775413626,"world":"BUYSILKCORSET"},{"accessible":true,"pos":[24,52],"price":15,"time":"2026-04-05 23:17:20","timestamp":1775420240,"world":"SUNIBA"},{"accessible":false,"pos":[81,46],"price":4,"time":"2026-04-08 11:58:17","timestamp":1775638697,"world":"7DR3"},{"accessible":true,"pos":[29,49],"price":12,"time":"2026-04-08 21:56:22","timestamp":1775674582,"world":"CUREBOI"},{"accessible":true,"pos":[40,23],"price":30,"time":"2026-04-09 15:38:35","timestamp":1775738315,"world":"TROPIQ"},{"accessible":false,"pos":[63,23],"price":13,"time":"2026-04-09 18:24:26","timestamp":1775748266,"world":"N7"}]