[{"accessible":true,"pos":[35,28],"price":11,"time":"2026-03-13 02:50:40","timestamp":1773359440,"world":"SUR"},{"accessible":false,"pos":[48,45],"price":15,"time":"2026-03-13 02:47:01","timestamp":1773359221,"world":"CURE2WL"},{"accessible":false,"pos":[27,37],"price":15,"time":"2026-03-13 02:49:51","timestamp":1773359391,"world":"BUYSURGEONS"},{"accessible":true,"pos":[41,44],"price":9,"time":"2026-03-13 02:50:10","timestamp":1773359410,"world":"TALLE"},{"accessible":true,"pos":[14,24],"price":20,"time":"2026-03-13 02:56:51","timestamp":1773359811,"world":"GGH"}]