[{"accessible":true,"pos":[29,31],"price":-4,"time":"2026-03-24 17:09:22","timestamp":1774361362,"world":"88BB"},{"accessible":true,"pos":[42,44],"price":-1,"time":"2026-03-25 02:07:15","timestamp":1774393635,"world":"FOLE"},{"accessible":true,"pos":[91,49],"price":-4,"time":"2026-03-27 10:17:37","timestamp":1774595857,"world":"MARTN"},{"accessible":true,"pos":[13,37],"price":-1,"time":"2026-04-02 15:31:17","timestamp":1775133077,"world":"24SF"},{"accessible":true,"pos":[89,30],"price":-4,"time":"2026-04-02 23:57:47","timestamp":1775163467,"world":"SIGMA"},{"accessible":true,"pos":[17,46],"price":-6,"time":"2026-04-04 02:59:08","timestamp":1775260748,"world":"ARAR"},{"accessible":true,"pos":[70,31],"price":-1,"time":"2026-04-05 08:44:26","timestamp":1775367866,"world":"SHOPCHASER"},{"accessible":true,"pos":[46,46],"price":-4,"time":"2026-04-07 20:49:13","timestamp":1775584153,"world":"VENDBKM"}]