[{"accessible":false,"pos":[35,7],"price":50,"time":"2026-04-17 02:34:38","timestamp":1776382478,"world":"JAJAN"},{"accessible":false,"pos":[37,10],"price":-1,"time":"2026-03-19 01:48:39","timestamp":1773874119,"world":"GC"},{"accessible":false,"pos":[65,31],"price":-1,"time":"2026-03-19 14:59:49","timestamp":1773921589,"world":"BUYHAT"},{"accessible":true,"pos":[95,22],"price":3,"time":"2026-03-20 01:14:02","timestamp":1773958442,"world":"BUYSETS2V"},{"accessible":false,"pos":[69,6],"price":-1,"time":"2026-04-07 13:16:27","timestamp":1775556987,"world":"VEND"},{"accessible":true,"pos":[66,46],"price":5,"time":"2026-04-10 01:50:41","timestamp":1775775041,"world":"DIOK"},{"accessible":true,"pos":[92,48],"price":8,"time":"2026-04-07 09:33:25","timestamp":1775543605,"world":"BUSANA"},{"accessible":false,"pos":[38,38],"price":-1,"time":"2026-04-25 15:13:46","timestamp":1777119226,"world":"U"},{"accessible":true,"pos":[60,44],"price":10,"time":"2026-04-18 14:15:36","timestamp":1776510936,"world":"PETM"}]