[{"accessible":true,"pos":[50,50],"price":85,"time":"2026-03-29 02:56:50","timestamp":1774742210,"world":"ZUAZ"},{"accessible":false,"pos":[65,51],"price":75,"time":"2026-03-16 14:02:15","timestamp":1773658935,"world":"BUYLIFEGOAL"},{"accessible":true,"pos":[35,51],"price":90,"time":"2026-03-18 22:39:47","timestamp":1773862787,"world":"ALTISHOP"},{"accessible":true,"pos":[67,47],"price":100,"time":"2026-03-24 17:21:52","timestamp":1774362112,"world":"88BB"},{"accessible":true,"pos":[44,28],"price":150,"time":"2026-04-03 21:52:56","timestamp":1775242376,"world":"YPR"},{"accessible":false,"pos":[32,7],"price":150,"time":"2026-03-29 02:47:48","timestamp":1774741668,"world":"FVE"},{"accessible":false,"pos":[82,14],"price":999,"time":"2026-03-29 21:13:50","timestamp":1774808030,"world":"SAMAA"},{"accessible":true,"pos":[13,42],"price":60,"time":"2026-03-30 20:01:56","timestamp":1774890116,"world":"CHC"},{"accessible":true,"pos":[45,44],"price":100,"time":"2026-04-03 20:43:41","timestamp":1775238221,"world":"DIOM"},{"accessible":true,"pos":[55,41],"price":83,"time":"2026-04-03 00:01:19","timestamp":1775163679,"world":"SIGMA"},{"accessible":false,"pos":[28,42],"price":14,"time":"2026-04-03 17:11:17","timestamp":1775225477,"world":"BUYEASTER"},{"accessible":false,"pos":[28,42],"price":180,"time":"2026-04-04 00:53:20","timestamp":1775253200,"world":"BUYEASTERXX"}]