[{"accessible":true,"pos":[17,18],"price":2,"time":"2026-03-17 21:28:49","timestamp":1773772129,"world":"PETM"},{"accessible":true,"pos":[81,21],"price":-1,"time":"2026-04-27 01:07:54","timestamp":1777241274,"world":"VENDML"},{"accessible":true,"pos":[31,45],"price":-1,"time":"2026-04-27 01:38:07","timestamp":1777243087,"world":"VENDALL"},{"accessible":false,"pos":[7,38],"price":4,"time":"2026-04-26 01:23:17","timestamp":1777155797,"world":"BUYSETS2V"},{"accessible":false,"pos":[94,19],"price":15,"time":"2026-04-29 16:09:18","timestamp":1777468158,"world":"CLOTHES"}]