[{"accessible":true,"pos":[34,7],"price":3000,"time":"2026-04-04 02:56:17","timestamp":1775260577,"world":"CHC"},{"accessible":true,"pos":[19,34],"price":5000,"time":"2026-04-17 02:51:41","timestamp":1776383501,"world":"JAJAN"},{"accessible":true,"pos":[34,27],"price":1800,"time":"2026-03-16 13:50:51","timestamp":1773658251,"world":"1MYT"},{"accessible":true,"pos":[43,25],"price":3000,"time":"2026-03-16 13:58:44","timestamp":1773658724,"world":"PQYQ"},{"accessible":true,"pos":[65,21],"price":7000,"time":"2026-03-20 16:41:53","timestamp":1774014113,"world":"DUSTAW"},{"accessible":true,"pos":[58,20],"price":3500,"time":"2026-03-30 03:01:12","timestamp":1774828872,"world":"TEYK"},{"accessible":true,"pos":[39,48],"price":1700,"time":"2026-03-25 21:09:00","timestamp":1774462140,"world":"D0CII"},{"accessible":true,"pos":[60,48],"price":1500,"time":"2026-03-27 01:36:15","timestamp":1774564575,"world":"KSACHEAP"},{"accessible":true,"pos":[71,5],"price":4500,"time":"2026-04-25 17:52:55","timestamp":1777128775,"world":"BUYSUPER"},{"accessible":true,"pos":[65,51],"price":1950,"time":"2026-04-06 00:40:20","timestamp":1775425220,"world":"DISTRO"},{"accessible":false,"pos":[51,39],"price":2000,"time":"2026-04-06 19:50:57","timestamp":1775494257,"world":"KSACHEAP"},{"accessible":true,"pos":[61,9],"price":2500,"time":"2026-04-07 18:14:44","timestamp":1775574884,"world":"BWOISS"},{"accessible":true,"pos":[70,40],"price":8000,"time":"2026-04-07 21:22:56","timestamp":1775586176,"world":"GBCS"},{"accessible":false,"pos":[59,7],"price":3800,"time":"2026-04-18 01:57:53","timestamp":1776466673,"world":"SULL"},{"accessible":true,"pos":[28,39],"price":2600,"time":"2026-04-19 20:03:54","timestamp":1776618234,"world":"ZJOX"},{"accessible":true,"pos":[10,38],"price":2000,"time":"2026-04-22 16:49:17","timestamp":1776865757,"world":"TOABI"},{"accessible":true,"pos":[30,38],"price":3000,"time":"2026-04-22 17:06:35","timestamp":1776866795,"world":"L0S"}]