[{"accessible":true,"pos":[26,48],"price":15,"time":"2026-03-15 23:55:02","timestamp":1773608102,"world":"JAJAN"},{"accessible":true,"pos":[36,43],"price":-1,"time":"2026-03-17 21:36:39","timestamp":1773772599,"world":"ECDY1"},{"accessible":true,"pos":[14,48],"price":-1,"time":"2026-03-17 21:44:07","timestamp":1773773047,"world":"PETM"},{"accessible":false,"pos":[89,33],"price":15,"time":"2026-03-19 15:16:02","timestamp":1773922562,"world":"WTU"},{"accessible":false,"pos":[9,52],"price":5,"time":"2026-03-25 02:12:34","timestamp":1774393954,"world":"CLOTHES"},{"accessible":true,"pos":[29,52],"price":-1,"time":"2026-04-04 02:58:32","timestamp":1775260712,"world":"GLOIR"}]