[{"accessible":false,"pos":[43,10],"price":19999,"time":"2026-04-17 02:36:35","timestamp":1776382595,"world":"JAJAN"},{"accessible":true,"pos":[28,23],"price":8000,"time":"2026-03-16 13:49:27","timestamp":1773658167,"world":"1MYT"},{"accessible":true,"pos":[87,49],"price":11500,"time":"2026-03-16 13:53:19","timestamp":1773658399,"world":"YUKJ"},{"accessible":false,"pos":[26,47],"price":19999,"time":"2026-03-18 21:07:38","timestamp":1773857258,"world":"GROCERY"},{"accessible":true,"pos":[89,32],"price":20000,"time":"2026-04-07 21:20:17","timestamp":1775586017,"world":"GBCS"},{"accessible":false,"pos":[57,45],"price":14999,"time":"2026-04-05 20:38:16","timestamp":1775410696,"world":"XBUYWING"},{"accessible":true,"pos":[42,15],"price":10000,"time":"2026-04-06 00:37:16","timestamp":1775425036,"world":"BWOISS"},{"accessible":true,"pos":[25,15],"price":17500,"time":"2026-04-24 16:34:12","timestamp":1777037652,"world":"BQM"},{"accessible":true,"pos":[33,39],"price":12000,"time":"2026-04-12 19:42:13","timestamp":1776012133,"world":"NQVL"},{"accessible":false,"pos":[57,22],"price":15900,"time":"2026-04-18 02:06:41","timestamp":1776467201,"world":"SULL"},{"accessible":true,"pos":[17,24],"price":15500,"time":"2026-04-16 01:03:08","timestamp":1776290588,"world":"WJAW"},{"accessible":false,"pos":[13,32],"price":14500,"time":"2026-04-29 00:28:06","timestamp":1777411686,"world":"62"}]