[{"accessible":true,"pos":[75,46],"price":-3,"time":"2026-03-16 14:00:43","timestamp":1773658843,"world":"DZEH"},{"accessible":true,"pos":[8,27],"price":-15,"time":"2026-03-21 04:09:13","timestamp":1774055353,"world":"SPIKED"},{"accessible":true,"pos":[58,13],"price":-5,"time":"2026-03-25 16:22:36","timestamp":1774444956,"world":"88BB"},{"accessible":true,"pos":[82,45],"price":-6,"time":"2026-03-27 10:16:43","timestamp":1774595803,"world":"MARTN"},{"accessible":true,"pos":[79,10],"price":-25,"time":"2026-03-31 01:21:55","timestamp":1774909315,"world":"BLOCKQO"},{"accessible":true,"pos":[97,43],"price":-12,"time":"2026-04-04 00:25:04","timestamp":1775251504,"world":"AWDMART"},{"accessible":true,"pos":[69,48],"price":-1,"time":"2026-04-04 03:00:35","timestamp":1775260835,"world":"ARAR"},{"accessible":true,"pos":[65,18],"price":-1,"time":"2026-04-05 08:33:25","timestamp":1775367205,"world":"UPYM"},{"accessible":true,"pos":[78,45],"price":-1,"time":"2026-04-05 08:48:47","timestamp":1775368127,"world":"SHOPCHASER"},{"accessible":true,"pos":[65,15],"price":-1,"time":"2026-04-05 19:59:29","timestamp":1775408369,"world":"EYEM"},{"accessible":true,"pos":[8,19],"price":-3,"time":"2026-04-07 20:42:53","timestamp":1775583773,"world":"VENDBKM"},{"accessible":true,"pos":[15,24],"price":-10,"time":"2026-04-07 20:44:27","timestamp":1775583867,"world":"SMVEND"}]