[{"accessible":true,"pos":[80,23],"price":3,"time":"2026-03-25 16:26:39","timestamp":1774445199,"world":"ALTISHOP"},{"accessible":true,"pos":[31,17],"price":3,"time":"2026-03-25 16:25:08","timestamp":1774445108,"world":"88BB"},{"accessible":true,"pos":[36,20],"price":2,"time":"2026-03-30 00:31:04","timestamp":1774819864,"world":"56X"},{"accessible":false,"pos":[84,21],"price":2,"time":"2026-04-02 18:43:50","timestamp":1775144630,"world":"BLOCKWOW"},{"accessible":true,"pos":[26,30],"price":1000,"time":"2026-04-05 08:43:55","timestamp":1775367835,"world":"SHOPCHASER"},{"accessible":true,"pos":[15,27],"price":2,"time":"2026-04-05 19:16:26","timestamp":1775405786,"world":"REKA"}]