[{"accessible":true,"pos":[95,23],"price":950,"time":"2026-03-10 16:46:14","timestamp":1773150374,"world":"FISDIKIT"},{"accessible":true,"pos":[56,43],"price":1200,"time":"2026-04-03 14:59:54","timestamp":1775217594,"world":"GEP214"},{"accessible":true,"pos":[48,40],"price":1200,"time":"2026-03-21 04:11:41","timestamp":1774055501,"world":"SPIKED"},{"accessible":true,"pos":[82,29],"price":1850,"time":"2026-03-21 20:29:31","timestamp":1774114171,"world":"TEYK"},{"accessible":true,"pos":[41,43],"price":2000,"time":"2026-04-23 00:36:23","timestamp":1776893783,"world":"88BB"},{"accessible":true,"pos":[53,43],"price":1000,"time":"2026-03-31 01:28:24","timestamp":1774909704,"world":"BLOCKQO"},{"accessible":true,"pos":[46,45],"price":1700,"time":"2026-03-31 16:46:14","timestamp":1774964774,"world":"7A1"},{"accessible":true,"pos":[47,33],"price":1350,"time":"2026-04-02 23:58:25","timestamp":1775163505,"world":"SIGMA"},{"accessible":true,"pos":[60,31],"price":2000,"time":"2026-04-07 21:19:47","timestamp":1775585987,"world":"GBCS"},{"accessible":true,"pos":[33,33],"price":1400,"time":"2026-04-04 00:05:27","timestamp":1775250327,"world":"BBPQ"},{"accessible":true,"pos":[42,49],"price":1300,"time":"2026-04-04 03:09:51","timestamp":1775261391,"world":"CHC"},{"accessible":true,"pos":[46,52],"price":2400,"time":"2026-04-05 19:57:18","timestamp":1775408238,"world":"JAYRONVENDS"},{"accessible":true,"pos":[35,39],"price":1750,"time":"2026-04-11 07:41:58","timestamp":1775882518,"world":"BLIP"},{"accessible":false,"pos":[61,5],"price":1250,"time":"2026-04-23 01:30:09","timestamp":1776897009,"world":"CORDON"},{"accessible":true,"pos":[41,43],"price":1300,"time":"2026-04-24 23:40:09","timestamp":1777063209,"world":"TROPIQ"}]