[{"accessible":false,"pos":[65,13],"price":3,"time":"2026-03-13 19:59:28","timestamp":1773421168,"world":"GEP214"},{"accessible":true,"pos":[56,16],"price":5,"time":"2026-03-11 16:47:30","timestamp":1773236850,"world":"GEP214"},{"accessible":true,"pos":[89,16],"price":3,"time":"2026-03-11 16:47:56","timestamp":1773236876,"world":"GEP214"},{"accessible":true,"pos":[96,25],"price":5,"time":"2026-03-11 16:51:39","timestamp":1773237099,"world":"GEP214"},{"accessible":false,"pos":[54,10],"price":5,"time":"2026-03-13 19:58:07","timestamp":1773421087,"world":"GEP214"},{"accessible":true,"pos":[71,29],"price":3,"time":"2026-03-13 13:13:42","timestamp":1773396822,"world":"H2QX"}]