[{"accessible":true,"pos":[84,26],"price":-20,"time":"2026-03-18 01:23:30","timestamp":1773786210,"world":"SLOU"},{"accessible":true,"pos":[5,41],"price":-1,"time":"2026-04-25 00:30:59","timestamp":1777066259,"world":"88BB"},{"accessible":true,"pos":[76,26],"price":-30,"time":"2026-03-23 15:59:28","timestamp":1774270768,"world":"432"},{"accessible":true,"pos":[29,26],"price":-40,"time":"2026-03-30 00:31:53","timestamp":1774819913,"world":"56X"},{"accessible":true,"pos":[56,16],"price":-50,"time":"2026-03-31 01:23:24","timestamp":1774909404,"world":"BLOCKQO"},{"accessible":true,"pos":[75,32],"price":-20,"time":"2026-04-01 04:45:16","timestamp":1775007916,"world":"TENKI"},{"accessible":true,"pos":[38,46],"price":-30,"time":"2026-04-01 22:59:25","timestamp":1775073565,"world":"DRLACHIMOLALA"},{"accessible":true,"pos":[60,51],"price":-82,"time":"2026-04-02 15:28:34","timestamp":1775132914,"world":"1OTE"},{"accessible":true,"pos":[44,36],"price":-1,"time":"2026-04-05 08:46:08","timestamp":1775367968,"world":"SHOPCHASER"},{"accessible":true,"pos":[77,32],"price":-15,"time":"2026-04-06 21:27:02","timestamp":1775500022,"world":"OTPO"},{"accessible":true,"pos":[5,49],"price":-15,"time":"2026-04-07 20:49:39","timestamp":1775584179,"world":"VENDBKM"},{"accessible":true,"pos":[3,41],"price":-3,"time":"2026-04-24 23:38:37","timestamp":1777063117,"world":"TROPIQ"},{"accessible":true,"pos":[71,4],"price":-10,"time":"2026-04-10 17:07:25","timestamp":1775830045,"world":"VERLICASHOP"},{"accessible":true,"pos":[45,23],"price":-30,"time":"2026-04-11 15:43:58","timestamp":1775911438,"world":"VENDALL"},{"accessible":false,"pos":[26,8],"price":-30,"time":"2026-04-15 20:23:31","timestamp":1776273811,"world":"PUBBI"},{"accessible":true,"pos":[87,51],"price":-25,"time":"2026-04-24 18:00:47","timestamp":1777042847,"world":"PPAWT"},{"accessible":true,"pos":[6,41],"price":-10,"time":"2026-04-25 00:02:23","timestamp":1777064543,"world":"BUYPEPPERV2"}]