[{"accessible":true,"pos":[69,25],"price":2500,"time":"2026-03-30 19:55:45","timestamp":1774889745,"world":"CHC"},{"accessible":false,"pos":[67,25],"price":2100,"time":"2026-03-17 01:53:52","timestamp":1773701632,"world":"NNUT"},{"accessible":true,"pos":[51,31],"price":1489,"time":"2026-03-15 23:44:55","timestamp":1773607495,"world":"JAJAN"},{"accessible":true,"pos":[90,40],"price":950,"time":"2026-03-20 15:24:15","timestamp":1774009455,"world":"YUKJ"},{"accessible":true,"pos":[68,33],"price":900,"time":"2026-03-23 16:45:37","timestamp":1774273537,"world":"H3GI"},{"accessible":false,"pos":[84,45],"price":3500,"time":"2026-03-25 03:39:47","timestamp":1774399187,"world":"EGO"},{"accessible":true,"pos":[84,31],"price":735,"time":"2026-03-29 02:44:01","timestamp":1774741441,"world":"KHMERSHOP"}]