[{"accessible":true,"pos":[18,37],"price":250,"time":"2026-03-20 15:22:39","timestamp":1774009359,"world":"YUKJ"},{"accessible":true,"pos":[81,38],"price":500,"time":"2026-03-21 20:33:06","timestamp":1774114386,"world":"TEYK"},{"accessible":true,"pos":[95,33],"price":215,"time":"2026-03-29 02:44:52","timestamp":1774741492,"world":"KHMERSHOP"},{"accessible":true,"pos":[80,13],"price":500,"time":"2026-04-06 00:36:57","timestamp":1775425017,"world":"BWOISS"},{"accessible":true,"pos":[51,44],"price":600,"time":"2026-04-08 14:05:02","timestamp":1775646302,"world":"WBOLO"}]