[{"accessible":false,"pos":[38,39],"price":10,"time":"2026-03-15 23:30:27","timestamp":1773606627,"world":"SELLHAND"},{"accessible":true,"pos":[30,31],"price":5,"time":"2026-03-23 21:45:16","timestamp":1774291516,"world":"JALANKA"},{"accessible":false,"pos":[85,45],"price":-2,"time":"2026-03-16 13:55:49","timestamp":1773658549,"world":"PHIRS"},{"accessible":true,"pos":[29,14],"price":2,"time":"2026-03-17 21:26:56","timestamp":1773772016,"world":"PETM"},{"accessible":false,"pos":[22,22],"price":3,"time":"2026-03-19 01:49:16","timestamp":1773874156,"world":"GC"},{"accessible":true,"pos":[7,31],"price":1,"time":"2026-04-05 18:42:48","timestamp":1775403768,"world":"YPR"},{"accessible":true,"pos":[42,32],"price":5,"time":"2026-03-26 23:34:53","timestamp":1774557293,"world":"BUYHAND"},{"accessible":true,"pos":[55,19],"price":8,"time":"2026-04-05 16:52:04","timestamp":1775397124,"world":"LIHEM"},{"accessible":true,"pos":[76,40],"price":3,"time":"2026-04-01 12:12:23","timestamp":1775034743,"world":"CIDD"},{"accessible":true,"pos":[95,43],"price":-1,"time":"2026-04-05 09:43:38","timestamp":1775371418,"world":"DIOM"},{"accessible":true,"pos":[74,50],"price":10,"time":"2026-04-02 18:43:56","timestamp":1775144636,"world":"LECA"},{"accessible":true,"pos":[72,46],"price":5,"time":"2026-04-04 12:58:07","timestamp":1775296687,"world":"DIOK"}]