[{"accessible":true,"pos":[77,48],"price":16000,"time":"2026-04-09 17:03:12","timestamp":1775743392,"world":"KOTEPONTIANAK"},{"accessible":false,"pos":[20,19],"price":20000,"time":"2026-04-18 02:04:29","timestamp":1776467069,"world":"SULL"},{"accessible":true,"pos":[30,30],"price":20000,"time":"2026-04-16 01:04:06","timestamp":1776290646,"world":"WJAW"},{"accessible":false,"pos":[54,42],"price":16000,"time":"2026-04-18 13:46:43","timestamp":1776509203,"world":"SEEDS"},{"accessible":false,"pos":[56,48],"price":18270,"time":"2026-04-29 00:34:20","timestamp":1777412060,"world":"62"}]