[{"accessible":true,"pos":[70,46],"price":5,"time":"2026-03-14 01:26:48","timestamp":1773440808,"world":"SUHARU"},{"accessible":true,"pos":[6,48],"price":150,"time":"2026-03-15 23:54:46","timestamp":1773608086,"world":"JAJAN"},{"accessible":false,"pos":[30,21],"price":55,"time":"2026-03-19 15:08:13","timestamp":1773922093,"world":"WTU"},{"accessible":false,"pos":[17,33],"price":20,"time":"2026-03-20 00:59:31","timestamp":1773957571,"world":"BUYWING"},{"accessible":false,"pos":[17,33],"price":100,"time":"2026-04-05 20:23:11","timestamp":1775409791,"world":"XBUYWING"},{"accessible":true,"pos":[70,22],"price":4,"time":"2026-03-22 15:31:06","timestamp":1774182666,"world":"GJFF"},{"accessible":true,"pos":[51,23],"price":8,"time":"2026-03-29 18:12:51","timestamp":1774797171,"world":"DAJAAL"},{"accessible":true,"pos":[10,19],"price":5,"time":"2026-04-03 14:48:59","timestamp":1775216939,"world":"JUYTINH"},{"accessible":true,"pos":[37,50],"price":25,"time":"2026-04-03 15:46:50","timestamp":1775220410,"world":"AWIKSMAIN"}]