[{"accessible":true,"pos":[22,13],"price":12500,"time":"2026-03-30 19:50:31","timestamp":1774889431,"world":"CHC"},{"accessible":true,"pos":[63,46],"price":19999,"time":"2026-04-17 03:01:08","timestamp":1776384068,"world":"JAJAN"},{"accessible":true,"pos":[56,46],"price":10999,"time":"2026-04-06 19:52:59","timestamp":1775494379,"world":"FASH"},{"accessible":true,"pos":[81,45],"price":13500,"time":"2026-04-22 16:54:42","timestamp":1776866082,"world":"VVE3"},{"accessible":false,"pos":[63,38],"price":13770,"time":"2026-04-29 00:31:24","timestamp":1777411884,"world":"62"}]